{
  "id": "content_centered",
  "type": "SharedSlice",
  "name": "ContentCentered",
  "description": "ContentCentered",
  "variations": [
    {
      "id": "default",
      "name": "Default",
      "docURL": "...",
      "version": "initial",
      "description": "Default",
      "imageUrl": "",
      "primary": {
        "eyebrow": {
          "type": "Text",
          "config": {
            "label": "Eyebrow",
            "placeholder": ""
          }
        },
        "heading": {
          "type": "Text",
          "config": {
            "label": "Heading",
            "placeholder": ""
          }
        },
        "intro": {
          "type": "Text",
          "config": {
            "label": "Intro",
            "placeholder": ""
          }
        },
        "paragraph1": {
          "type": "StructuredText",
          "config": {
            "label": "Paragraph1",
            "placeholder": "",
            "allowTargetBlank": true,
            "multi": "paragraph,preformatted,heading1,heading2,heading3,heading4,heading5,heading6,strong,em,hyperlink,image,embed,list-item,o-list-item,rtl"
          }
        },
        "bullets": {
          "type": "Group",
          "config": {
            "label": "Bullets",
            "repeat": true,
            "fields": {
              "bold": {
                "type": "Text",
                "config": {
                  "label": "Bold",
                  "placeholder": ""
                }
              },
              "content": {
                "type": "Text",
                "config": {
                  "label": "Content",
                  "placeholder": ""
                }
              }
            }
          }
        },
        "paragraph2": {
          "type": "StructuredText",
          "config": {
            "label": "Paragraph2",
            "placeholder": "",
            "allowTargetBlank": true,
            "multi": "paragraph,preformatted,heading1,heading2,heading3,heading4,heading5,heading6,strong,em,hyperlink,image,embed,list-item,o-list-item,rtl"
          }
        }
      },
      "items": {}
    }
  ]
}